{
  "converged": true,
  "iterations": 15,
  "equilibrium": {
    "z_offset_mm": -371.47,
    "pitch_deg": -1.2539,
    "roll_deg": 0.1825
  },
  "center_of_gravity_body": {
    "x": -0.0,
    "y": -145.74,
    "z": 581.36
  },
  "center_of_gravity_world": {
    "x": -0.06,
    "y": -146.1,
    "z": 205.14
  },
  "center_of_buoyancy": {
    "x": 0.63,
    "y": -145.46,
    "z": -142.36
  },
  "total_mass_kg": 825.83,
  "weight_N": 8101.39,
  "buoyancy_force_N": 8099.94,
  "submerged_volume_liters": 805.54,
  "hull_groups": {
    "hull": {
      "submerged_volume_liters": 805.5,
      "total_volume_liters": 5050.2,
      "submerged_percent": 15.9,
      "z_world_mm": -1275.0
    }
  },
  "final_residuals": {
    "force": -0.000179,
    "pitch_moment": 0.000637,
    "roll_moment": 0.000689,
    "norm": 0.000955
  },
  "iteration_history": [
    {
      "iteration": 0,
      "z_mm": -373.54,
      "pitch_deg": 0.0,
      "roll_deg": 0.0,
      "residual_norm": 0.136372,
      "force_residual": 0.008327,
      "pitch_residual": -0.13601,
      "roll_residual": -0.0054,
      "buoyancy_N": 8168.85,
      "submerged_liters": 812.4,
      "group_breakdown": {
        "hull": {
          "submerged_liters": 812.4,
          "total_liters": 5050.2,
          "z_world": -1274.0
        }
      }
    },
    {
      "iteration": 1,
      "z_mm": -359.45,
      "pitch_deg": -0.0707,
      "roll_deg": 0.3325,
      "residual_norm": 0.132726,
      "force_residual": -0.035135,
      "pitch_residual": -0.127943,
      "roll_residual": -0.003538,
      "buoyancy_N": 7816.75,
      "submerged_liters": 777.38,
      "group_breakdown": {
        "hull": {
          "submerged_liters": 777.4,
          "total_liters": 5050.2,
          "z_world": -1260.0
        }
      }
    },
    {
      "iteration": 2,
      "z_mm": -381.85,
      "pitch_deg": -1.706,
      "roll_deg": -1.6731,
      "residual_norm": 0.090573,
      "force_residual": 0.068271,
      "pitch_residual": 0.059031,
      "roll_residual": -0.007615,
      "buoyancy_N": 8654.48,
      "submerged_liters": 860.69,
      "group_breakdown": {
        "hull": {
          "submerged_liters": 860.7,
          "total_liters": 5050.2,
          "z_world": -1285.0
        }
      }
    },
    {
      "iteration": 3,
      "z_mm": -376.67,
      "pitch_deg": -1.781,
      "roll_deg": -1.6036,
      "residual_norm": 0.032996,
      "force_residual": 0.003765,
      "pitch_residual": 0.032438,
      "roll_residual": -0.004728,
      "buoyancy_N": 8131.89,
      "submerged_liters": 808.72,
      "group_breakdown": {
        "hull": {
          "submerged_liters": 808.7,
          "total_liters": 5050.2,
          "z_world": -1280.0
        }
      }
    },
    {
      "iteration": 4,
      "z_mm": -365.9,
      "pitch_deg": -1.0494,
      "roll_deg": -0.3536,
      "residual_norm": 0.017266,
      "force_residual": 0.002196,
      "pitch_residual": 0.016361,
      "roll_residual": -0.00506,
      "buoyancy_N": 8119.18,
      "submerged_liters": 807.46,
      "group_breakdown": {
        "hull": {
          "submerged_liters": 807.5,
          "total_liters": 5050.2,
          "z_world": -1269.0
        }
      }
    },
    {
      "iteration": 5,
      "z_mm": -365.4,
      "pitch_deg": -1.0555,
      "roll_deg": -0.3645,
      "residual_norm": 0.053457,
      "force_residual": -0.047431,
      "pitch_residual": 0.024013,
      "roll_residual": -0.005594,
      "buoyancy_N": 7717.13,
      "submerged_liters": 767.47,
      "group_breakdown": {
        "hull": {
          "submerged_liters": 767.5,
          "total_liters": 5050.2,
          "z_world": -1268.0
        }
      }
    },
    {
      "iteration": 6,
      "z_mm": -375.38,
      "pitch_deg": -1.1995,
      "roll_deg": -0.2159,
      "residual_norm": 0.050503,
      "force_residual": 0.019103,
      "pitch_residual": 0.046469,
      "roll_residual": -0.00513,
      "buoyancy_N": 8256.15,
      "submerged_liters": 821.08,
      "group_breakdown": {
        "hull": {
          "submerged_liters": 821.1,
          "total_liters": 5050.2,
          "z_world": -1278.0
        }
      }
    },
    {
      "iteration": 7,
      "z_mm": -375.46,
      "pitch_deg": -1.1984,
      "roll_deg": -0.1924,
      "residual_norm": 0.03146,
      "force_residual": 0.031297,
      "pitch_residual": -0.002781,
      "roll_residual": -0.001572,
      "buoyancy_N": 8354.94,
      "submerged_liters": 830.9,
      "group_breakdown": {
        "hull": {
          "submerged_liters": 830.9,
          "total_liters": 5050.2,
          "z_world": -1278.0
        }
      }
    },
    {
      "iteration": 8,
      "z_mm": -375.4,
      "pitch_deg": -1.1996,
      "roll_deg": -0.1925,
      "residual_norm": 0.072322,
      "force_residual": 0.062649,
      "pitch_residual": 0.035849,
      "roll_residual": -0.004522,
      "buoyancy_N": 8608.93,
      "submerged_liters": 856.16,
      "group_breakdown": {
        "hull": {
          "submerged_liters": 856.2,
          "total_liters": 5050.2,
          "z_world": -1278.0
        }
      }
    },
    {
      "iteration": 9,
      "z_mm": -360.69,
      "pitch_deg": -1.1533,
      "roll_deg": -0.0129,
      "residual_norm": 0.045797,
      "force_residual": -0.038767,
      "pitch_residual": 0.024154,
      "roll_residual": -0.003324,
      "buoyancy_N": 7787.32,
      "submerged_liters": 774.45,
      "group_breakdown": {
        "hull": {
          "submerged_liters": 774.5,
          "total_liters": 5050.2,
          "z_world": -1264.0
        }
      }
    },
    {
      "iteration": 10,
      "z_mm": -362.24,
      "pitch_deg": -1.1755,
      "roll_deg": 0.0126,
      "residual_norm": 0.038425,
      "force_residual": -0.031038,
      "pitch_residual": 0.022531,
      "roll_residual": -0.002346,
      "buoyancy_N": 7849.94,
      "submerged_liters": 780.68,
      "group_breakdown": {
        "hull": {
          "submerged_liters": 780.7,
          "total_liters": 5050.2,
          "z_world": -1265.0
        }
      }
    },
    {
      "iteration": 11,
      "z_mm": -370.38,
      "pitch_deg": -1.2207,
      "roll_deg": 0.0848,
      "residual_norm": 0.027729,
      "force_residual": -0.018681,
      "pitch_residual": -0.020444,
      "roll_residual": 0.001397,
      "buoyancy_N": 7950.05,
      "submerged_liters": 790.64,
      "group_breakdown": {
        "hull": {
          "submerged_liters": 790.6,
          "total_liters": 5050.2,
          "z_world": -1273.0
        }
      }
    },
    {
      "iteration": 12,
      "z_mm": -370.5,
      "pitch_deg": -1.2217,
      "roll_deg": 0.0824,
      "residual_norm": 0.026425,
      "force_residual": 0.01571,
      "pitch_residual": 0.021176,
      "roll_residual": -0.001743,
      "buoyancy_N": 8228.66,
      "submerged_liters": 818.34,
      "group_breakdown": {
        "hull": {
          "submerged_liters": 818.3,
          "total_liters": 5050.2,
          "z_world": -1274.0
        }
      }
    },
    {
      "iteration": 13,
      "z_mm": -371.26,
      "pitch_deg": -1.2581,
      "roll_deg": -0.0075,
      "residual_norm": 0.022952,
      "force_residual": 0.013986,
      "pitch_residual": 0.018138,
      "roll_residual": -0.001472,
      "buoyancy_N": 8214.7,
      "submerged_liters": 816.96,
      "group_breakdown": {
        "hull": {
          "submerged_liters": 817.0,
          "total_liters": 5050.2,
          "z_world": -1274.0
        }
      }
    },
    {
      "iteration": 14,
      "z_mm": -371.47,
      "pitch_deg": -1.2539,
      "roll_deg": 0.1825,
      "residual_norm": 0.000955,
      "force_residual": -0.000179,
      "pitch_residual": 0.000637,
      "roll_residual": 0.000689,
      "buoyancy_N": 8099.94,
      "submerged_liters": 805.54,
      "group_breakdown": {
        "hull": {
          "submerged_liters": 805.5,
          "total_liters": 5050.2,
          "z_world": -1275.0
        }
      }
    }
  ],
  "validator": "buoyancy"
}